__init__.py
function/__init__.py
function/plots.py
function/timer.py
function/variables.py
io/__init__.py
io/dataio.py
io/plot3dio.py
streamlines/__init__.py
streamlines/integration.py
streamlines/interpolation.py
streamlines/search.py
streamlines/stochastic_model.py
streamlines/streamlines.py
test_cases/__init__.py
test_cases/oblique_shock_data.py
lpttools-0.1.4a2.dist-info/LICENSE
lpttools-0.1.4a2.dist-info/METADATA
lpttools-0.1.4a2.dist-info/WHEEL
lpttools-0.1.4a2.dist-info/top_level.txt
lpttools-0.1.4a2.dist-info/RECORD
