Metadata-Version: 2.1
Name: lpttools
Version: 0.1.4a2
Summary: One-way coupled Lagrangian Particle Tracking for CFD simulations. Includes many auxiliary tools.
Author-email: Dilip Kalagotla <dilipkalagotla@gmail.com>
Project-URL: homepage, https://github.com/kalagotla/project-arrakis
Project-URL: issues, https://github.com/kalagotla/project-arrakis/issues
Classifier: Programming Language :: Python :: 3
Classifier: License :: OSI Approved :: MIT License
Classifier: Operating System :: OS Independent
Requires-Python: >=3.10
License-File: LICENSE
Requires-Dist: numpy
Requires-Dist: scipy
Requires-Dist: matplotlib
Requires-Dist: pandas
Requires-Dist: seaborn
Requires-Dist: tqdm
